datacanopy/__init__.py
datacanopy-0.0.2.dist-info/METADATA
datacanopy-0.0.2.dist-info/WHEEL
datacanopy-0.0.2.dist-info/RECORD
