Metadata-Version: 2.4
Name: datacanopy
Version: 0.0.2
Summary: Semantic versioning for ML datasets
Project-URL: Homepage, https://github.com/datacanopy/datacanopy
Project-URL: Repository, https://github.com/datacanopy/datacanopy
Author-email: Kevin Winkler <kevin.winkler1@gmail.com>
License: MIT
Classifier: Development Status :: 2 - Pre-Alpha
Classifier: Intended Audience :: Developers
Classifier: License :: OSI Approved :: MIT License
Classifier: Programming Language :: Python :: 3
Classifier: Programming Language :: Python :: 3.10
Classifier: Programming Language :: Python :: 3.11
Classifier: Programming Language :: Python :: 3.12
Requires-Python: >=3.10
